genpipes/__init__.py
genpipes/compose.py
genpipes/declare.py
genpipes-2.0.1.dist-info/LICENSE
genpipes-2.0.1.dist-info/WHEEL
genpipes-2.0.1.dist-info/METADATA
genpipes-2.0.1.dist-info/RECORD
