Metadata-Version: 2.1
Name: genpipes
Version: 2.0.1
Summary: Simple library to compose pipeline in the sklearn way thanks to generators
Home-page: https://github.com/Mg30/genpipes
Author: Matt G.
Requires-Python: >=3.8.0,<4.0.0
Classifier: Programming Language :: Python :: 3
Classifier: Programming Language :: Python :: 3.8
Classifier: Programming Language :: Python :: 3.9
Classifier: Programming Language :: Python :: 3.10
Classifier: Programming Language :: Python :: 3.11
Project-URL: Repository, https://github.com/Mg30/genpipes
